pathlib_artifactory.py
pathlib_artifactory-0.4.1.dist-info/licenses/LICENSE
pathlib_artifactory-0.4.1.dist-info/METADATA
pathlib_artifactory-0.4.1.dist-info/WHEEL
pathlib_artifactory-0.4.1.dist-info/top_level.txt
pathlib_artifactory-0.4.1.dist-info/RECORD
